powerrag/sdk/README.md
powerrag/sdk/__init__.py
powerrag/sdk/client.py
powerrag/sdk/modules/chunk.py
powerrag/sdk/modules/chunk_manager.py
powerrag/sdk/modules/document.py
powerrag/sdk/modules/document_manager.py
powerrag/sdk/modules/extraction.py
powerrag/sdk/modules/extraction_manager.py
powerrag/sdk/modules/knowledge_base.py
powerrag/sdk/modules/knowledge_base_manager.py
powerrag/sdk/modules/knowledge_graph.py
powerrag/sdk/modules/knowledge_graph_manager.py
powerrag/sdk/modules/raptor.py
powerrag/sdk/modules/raptor_manager.py
powerrag/sdk/modules/retrieval.py
powerrag/sdk/modules/retrieval_manager.py
powerrag/sdk/pyproject.toml
powerrag_sdk-0.3.0.dist-info/METADATA
powerrag_sdk-0.3.0.dist-info/WHEEL
powerrag_sdk-0.3.0.dist-info/licenses/LICENSE
powerrag_sdk-0.3.0.dist-info/RECORD
