Metadata-Version: 2.4
Name: powerrag-sdk
Version: 0.3.0
Summary: A Python SDK for PowerRAG API, providing easy-to-use interfaces for knowledge base management, document processing, chunking, extraction, RAPTOR, knowledge graph, and retrieval.
License: Apache-2.0
License-File: LICENSE
Keywords: powerrag,rag,llm,sdk,knowledge-base,document-processing
Author: OceanBase Team
Author-email: contact@oceanbase.com
Requires-Python: >=3.10,<4.0
Classifier: Development Status :: 4 - Beta
Classifier: Intended Audience :: Developers
Classifier: License :: OSI Approved :: Apache Software License
Classifier: Programming Language :: Python :: 3
Classifier: Programming Language :: Python :: 3.10
Classifier: Programming Language :: Python :: 3.11
Classifier: Programming Language :: Python :: 3.12
Classifier: Programming Language :: Python :: 3.13
Classifier: Programming Language :: Python :: 3.14
Classifier: Programming Language :: Python :: 3.9
Classifier: Topic :: Software Development :: Libraries :: Python Modules
Requires-Dist: requests (>=2.28.0)
Requires-Dist: typing-extensions (>=4.0.0) ; python_version < "3.11"
Project-URL: Bug Tracker, https://github.com/oceanbase/powerrag/issues
Project-URL: Documentation, https://github.com/oceanbase/powerrag/docs
Project-URL: Homepage, https://github.com/oceanbase/powerrag
Project-URL: Repository, https://github.com/oceanbase/powerrag
Project-URL: Source Code, https://github.com/oceanbase/powerrag
